clang_repl_kernel/.gitattributes
clang_repl_kernel/ClangReplInterface.py
clang_repl_kernel/__init__.py
clang_repl_kernel/__main__.py
clang_repl_kernel/downloader.py
clang_repl_kernel/install.py
clang_repl_kernel/kernel.py
clang_repl_kernel/test_kernel.py
clang_repl_kernel/.idea/.gitignore
clang_repl_kernel/.idea/clang_repl_kernel.iml
clang_repl_kernel/.idea/deployment.xml
clang_repl_kernel/.idea/misc.xml
clang_repl_kernel/.idea/modules.xml
clang_repl_kernel/.idea/vcs.xml
clang_repl_kernel/.idea/workspace.xml
clang_repl_kernel/.idea/inspectionProfiles/Project_Default.xml
clang_repl_kernel/.idea/inspectionProfiles/profiles_settings.xml
clang_repl_kernel-1.6.26.data/data/share/jupyter/kernels/clang_repl_cpp14/kernel.json
clang_repl_kernel-1.6.26.data/data/share/jupyter/kernels/clang_repl_cpp17/kernel.json
clang_repl_kernel-1.6.26.data/data/share/jupyter/kernels/clang_repl_cpp20/kernel.json
clang_repl_kernel-1.6.26.data/data/share/jupyter/kernels/clang_repl_cpp23/kernel.json
clang_repl_kernel-1.6.26.dist-info/METADATA
clang_repl_kernel-1.6.26.dist-info/WHEEL
clang_repl_kernel-1.6.26.dist-info/licenses/LICENSE
clang_repl_kernel-1.6.26.dist-info/RECORD
