Metadata-Version: 2.4
Name: clang-repl-kernel
Version: 1.6.26
Summary: Clang-REPL kernel for Jupyter
Project-URL: Homepage, https://github.com/ormastes/jupyter_kernels/tree/main/clang_repl_kernel
Author-email: "Yoon, Jonghyun" <ormastes@naver.com>
License:                                  Apache License
License-File: LICENSE
Classifier: Intended Audience :: Developers
Classifier: License :: OSI Approved :: Apache Software License
Classifier: Programming Language :: Python :: 3
Requires-Python: >=3.11
Requires-Dist: ipykernel
Requires-Dist: jupyter-client
Requires-Dist: tqdm
Requires-Dist: traitlets
